commercetools/__init__.py
commercetools/client.py
commercetools/helpers.py
commercetools/paginators.py
commercetools/schemas.py
commercetools/types.py
commercetools/typing.py
commercetools/utils.py
commercetools/contrib/__init__.py
commercetools/contrib/pytest.py
commercetools/services/__init__.py
commercetools/services/abstract.py
commercetools/services/carts.py
commercetools/services/categories.py
commercetools/services/channels.py
commercetools/services/custom_objects.py
commercetools/services/extensions.py
commercetools/services/inventory.py
commercetools/services/orders.py
commercetools/services/payments.py
commercetools/services/product_projections.py
commercetools/services/product_types.py
commercetools/services/products.py
commercetools/services/project.py
commercetools/services/shipping_methods.py
commercetools/services/subscriptions.py
commercetools/services/tax_categories.py
commercetools/services/types.py
commercetools/testing/__init__.py
commercetools/testing/abstract.py
commercetools/testing/auth.py
commercetools/testing/categories.py
commercetools/testing/channels.py
commercetools/testing/custom_objects.py
commercetools/testing/extensions.py
commercetools/testing/inventory.py
commercetools/testing/payments.py
commercetools/testing/predicates.py
commercetools/testing/product_projections.py
commercetools/testing/product_types.py
commercetools/testing/products.py
commercetools/testing/project.py
commercetools/testing/server.py
commercetools/testing/shipping_methods.py
commercetools/testing/subscriptions.py
commercetools/testing/tax_categories.py
commercetools/testing/types.py
commercetools/testing/utils.py
commercetools_ratdev-1.5.1.dist-info/LICENSE
commercetools_ratdev-1.5.1.dist-info/METADATA
commercetools_ratdev-1.5.1.dist-info/WHEEL
commercetools_ratdev-1.5.1.dist-info/top_level.txt
commercetools_ratdev-1.5.1.dist-info/RECORD
