Metadata-Version: 2.1
Name: commercetools-ratdev
Version: 1.5.1
Summary: Ratan's fork of SDK for Commercetools
Home-page: https://github.co/labd/commercetools-python-sdk
Author: Lab Digital B.V.
Author-email: opensource@labdigital.nl
License: MIT
Platform: UNKNOWN
Classifier: Development Status :: 5 - Production/Stable
Classifier: License :: OSI Approved :: MIT License
Classifier: Programming Language :: Python :: 3
Classifier: Programming Language :: Python :: 3.6
Classifier: Programming Language :: Python :: 3.7
Classifier: Programming Language :: Python :: Implementation :: CPython
Requires-Dist: requests (>=2.7.0)
Requires-Dist: pytz
Requires-Dist: requests-oauthlib (>=1.0.0)
Requires-Dist: attrs (>=18.2.0)
Requires-Dist: marshmallow (>=3.0.0b17)
Requires-Dist: marshmallow-enum (==1.4.1)
Requires-Dist: WebOb (==1.8.4)
Requires-Dist: wrapt (==1.10.0)
Provides-Extra: codegen
Requires-Dist: PyYAML (==3.13) ; extra == 'codegen'
Requires-Dist: astunparse (==1.6.1) ; extra == 'codegen'
Requires-Dist: black (==18.9b0) ; extra == 'codegen'
Requires-Dist: isort ; extra == 'codegen'
Provides-Extra: docs
Requires-Dist: Sphinx (>=1.8.1) ; extra == 'docs'
Requires-Dist: sphinx-rtd-theme (==0.4.2) ; extra == 'docs'
Requires-Dist: sphinx-autodoc-typehints (==1.4.0) ; extra == 'docs'
Provides-Extra: test
Requires-Dist: freezegun (==0.3.8) ; extra == 'test'
Requires-Dist: mock (==2.0.0) ; extra == 'test'
Requires-Dist: pretend (==1.0.8) ; extra == 'test'
Requires-Dist: pytest-cov (==2.5.1) ; extra == 'test'
Requires-Dist: pytest (==3.1.3) ; extra == 'test'
Requires-Dist: requests-mock (>=0.7.0) ; extra == 'test'
Requires-Dist: isort (==4.2.15) ; extra == 'test'
Requires-Dist: flake8 (==3.3.0) ; extra == 'test'
Requires-Dist: flake8-blind-except (==0.1.1) ; extra == 'test'
Requires-Dist: flake8-debugger (==1.4.0) ; extra == 'test'
Requires-Dist: flake8-imports (==0.1.1) ; extra == 'test'
Requires-Dist: mypy (==0.630) ; extra == 'test'
